pypino/__init__.py
pypino/pypino.py
pypino-0.1.0.dist-info/LICENSE
pypino-0.1.0.dist-info/METADATA
pypino-0.1.0.dist-info/WHEEL
pypino-0.1.0.dist-info/top_level.txt
pypino-0.1.0.dist-info/RECORD
