Metadata-Version: 2.1
Name: pypino
Version: 0.1.0
Summary: A Python JSON logger with output matching Pino.js
Home-page: https://github.com/Brayyy/pypino
Author: Bray Almini
Author-email: bray@coreforge.com
License: MIT
Download-URL: https://github.com/Brayyy/pypino/tarball/0.1.0
Keywords: log,logging,json,pino
Platform: UNKNOWN
Classifier: Programming Language :: Python :: 2.6
Classifier: Programming Language :: Python :: 2.7
Classifier: Programming Language :: Python :: 3.0
Classifier: Programming Language :: Python :: 3.6
Classifier: License :: OSI Approved :: MIT License
Classifier: Operating System :: OS Independent
